setup.py
tvd/__init__.py
tvd/dvd.py
tvd/rip.py
tvd/tvseries.py
tvd.egg-info/PKG-INFO
tvd.egg-info/SOURCES.txt
tvd.egg-info/dependency_links.txt
tvd.egg-info/requires.txt
tvd.egg-info/top_level.txt
tvd/test/__init__.py
tvd/test/data
tvd/test/test_dvd.py